{
  "生成时间": "2025-10-12T12:20:00.000Z",
  "说明": "极简版 hush-ops 仅保留业务相关脚本与 CLI 入口，运维自动化已删除。",
  "资产清单": [
    { "类型": "npm-script", "名称": "dev", "入口": "npm run dev", "命令": "npm run ui:dev" },
    { "类型": "npm-script", "名称": "service:start", "入口": "npm run service:start", "命令": "tsx src/service/orchestrator/start.ts" },
    { "类型": "npm-script", "名称": "service:prod", "入口": "npm run service:prod", "命令": "node dist/src/service/orchestrator/start.js" },
    { "类型": "npm-script", "名称": "build", "入口": "npm run build", "命令": "tsc -p tsconfig.json" },
    { "类型": "npm-script", "名称": "lint", "入口": "npm run lint", "命令": "eslint \"{src,examples}/**/*.ts\" --max-warnings=0" },
    { "类型": "npm-script", "名称": "test", "入口": "npm run test", "命令": "vitest run" },
    { "类型": "npm-script", "名称": "typecheck", "入口": "npm run typecheck", "命令": "tsc --noEmit && tsc --noEmit -p tsconfig.ui.json" },
    { "类型": "npm-script", "名称": "agents:config", "入口": "npm run agents:config -- <command>", "命令": "tsx src/cli/index.ts agents:config" },
    { "类型": "npm-script", "名称": "approvals", "入口": "npm run approvals -- <command>", "命令": "tsx src/cli/index.ts approvals" },
    { "类型": "npm-script", "名称": "cli", "入口": "npm run cli -- <command>", "命令": "tsx src/cli/index.ts" },
    { "类型": "npm-script", "名称": "ui:dev", "入口": "npm run ui:dev", "命令": "vite --config vite.config.ts" },
    { "类型": "npm-script", "名称": "ui:build", "入口": "npm run ui:build", "命令": "vite build --config vite.config.ts" },
    { "类型": "npm-script", "名称": "ui:preview", "入口": "npm run ui:preview", "命令": "vite preview --config vite.config.ts" },
    { "类型": "npm-script", "名称": "ui:ga", "入口": "npm run ui:ga", "命令": "npm run typecheck && vitest run tests/ui/planTransforms.spec.ts tests/ui/PendingApprovals.spec.tsx" }
  ]
}
